_jsonnet.cpython-310-darwin.so
sentry_forked_jsonnet-0.20.0.post4.dist-info/RECORD
sentry_forked_jsonnet-0.20.0.post4.dist-info/LICENSE
sentry_forked_jsonnet-0.20.0.post4.dist-info/WHEEL
sentry_forked_jsonnet-0.20.0.post4.dist-info/top_level.txt
sentry_forked_jsonnet-0.20.0.post4.dist-info/METADATA
