Metadata-Version: 2.1
Name: sentry-forked-jsonnet
Version: 0.20.0.post4
Summary: Python bindings for Jsonnet - The data templating language 
Home-page: https://jsonnet.org
Author: David Cunningham
Author-email: dcunnin@google.com
License: Apache License 2.0
Project-URL: Source, https://github.com/google/jsonnet
License-File: LICENSE
